Workbook

Sheet Read me
A1: Correspondent banking respondent risk model
A2: Version 0.1 — draft for team review
A4: Purpose | B4: Scores the inherent and residual financial crime risk of a prospective correspondent banking respondent institution, from the information supplied in a completed Wolfsberg CBDDQ and supporting evidence.
A5: Scope | B5: One change type only: onboarding a new cross-border correspondent banking respondent. Not customer onboarding, not new product launch, not geographic expansion.
A6: Design rule 1 | B6: The AI reads and writes. This model decides. Extraction produces facts; this workbook produces the number. No model output is ever a score.
A7: Design rule 2 | B7: Weights are configuration, not code. Every weight on the Factors and weights sheet is an input cell. Changes are recorded on the Change log sheet with a justification, and each assessment records which version scored it.
A8: Design rule 3 | B8: Controls reduce risk; they never eliminate it. Residual risk is floored at 20 per cent of inherent risk. A respondent with every control independently evidenced still carries a fifth of its inherent risk.
A9: Grounding | B9: Risk categories follow the FFIEC BSA/AML Examination Manual (March 2020), BSA/AML Risk Assessment section. Individual factors and the control set map to named FATF 40 Recommendations (2003, as amended to 2004). Source questions map to the Wolfsberg Group CBDDQ V1.4.
A10: FFIEC support | B10: The manual states that there are no required risk categories and that a bank may determine that some factors should be weighted more heavily than others, adding that sound practice is to document the factors considered including any weighting. That is what this workbook is. It also warns that no single indicator determines a higher or lower risk profile, which is why no single factor can move a case to prohibited on its own.
A11: Hard exclusions | B11: Separate from the weighted model. FATF Recommendation 18 is a prohibition rather than a risk weight, so shell bank determinations are a binary stop applied before scoring. See the Hard exclusions sheet.
A12: How to use | B12: Read Framework map first. Set weights on Factors and weights. Score a case on Calculator by entering the six factor scores and the four control evidence tiers. Compare against the three worked examples on Worked cases.
A13: Cell colours | B13: Blue text = an input you set. Black text = a formula, do not overtype. Yellow fill = a key assumption the team should argue about before it is frozen.
A14: Open question | B14: The 0 / 3 / 6 / 10 anchors are deliberately coarse. Finer granularity would imply a precision the source documents do not support. Revisit if eval shows analysts overriding a band repeatedly at one boundary.

Sheet Framework map
A1: Every factor and control traces to a published source
A3: ID | B3: Factor or control | C3: FFIEC risk category | D3: FATF Recommendation | E3: Wolfsberg CBDDQ V1.4 source questions
A4: F1 | B4: Jurisdiction and geographic footprint | C4: Geographic locations | D4: Rec 21 (countries that insufficiently apply the Recommendations); Rec 22 (branches and subsidiaries abroad) | E4: Q2 foreign branches; Q3 registered address; Q13 jurisdiction of ultimate parent; Q15a non-resident customer countries; Q108 presence in comprehensively sanctioned jurisdictions
A5: F2 | B5: Quality of supervision and regulatory standing | C5: Customers and entities | D5: Rec 7(a) (understand the respondent, determine reputation and quality of supervision, and whether subject to investigation or regulatory action); Rec 23 | E5: Q10 primary regulator; Q11 LEI; Q13 licensing authority of ultimate parent
A6: F3 | B6: Ownership and control transparency | C6: Customers and entities | D6: Rec 5(b) (identify beneficial owner, understand ownership and control structure); Rec 33 (bearer shares) | E6: Q6 ownership type; Q6d1 shareholders or UBOs at 10 per cent or more; Q7 bearer shares; Q12 ultimate parent
A7: F4 | B7: Physical presence and shell bank proximity | C7: Customers and entities | D7: Rec 18 (shell banks); Glossary definition of shell bank | E7: Q3 and Q4 addresses; Q8 offshore banking licence; Q9 virtual bank licence or online-only channels
A8: F5 | B8: Products, services and delivery channels | C8: Products and services | D8: Rec 7(e) (payable-through accounts); Rec 8 (non-face-to-face and new technologies); Rec 11 (complex or unusual transactions) | E8: Q14 business areas; Q19a to Q19q products offered including correspondent banking, payable-through accounts, hold mail, virtual assets, remittances
A9: F6 | B9: Customer base and PEP exposure | C9: Customers and entities | D9: Rec 6 (politically exposed persons) | E9: Q15 non-resident customer concentration; Q71 to Q73 PEP screening; Q76 restricted and prohibited customer categories
A10: C1 | B10: AML, CTF and sanctions programme with independent testing | C10: n/a — control | D10: Rec 15 (internal policies, training, audit function to test the system) | E10: Q22a to Q22l programme components, in particular Q22g independent testing
A11: C2 | B11: Customer due diligence and beneficial ownership | C11: n/a — control | D11: Rec 5 (CDD); Rec 10 (record keeping) | E11: Q22c beneficial ownership; Q22e CDD; Q22f EDD; Q74 periodic review frequency
A12: C3 | B12: Sanctions and PEP screening | C12: n/a — control | D12: Rec 6 (PEPs); Rec 13 (suspicious transaction reporting) | E12: Q70 adverse media method; Q72 PEP screening method; Q106 sanctions lists used; Q107 list update timeliness
A13: C4 | B13: Correspondent and downstream relationship controls | C13: n/a — control | D13: Rec 7(a) to 7(e); Rec 18 (guard against accounts used by shell banks) | E13: Q19a1c and Q19a1f downstream identification procedures; Q19h payable-through accounts; Q76t shell banks prohibited; Q78 senior management approval for EDD
A15: Note: FATF revised the 40 Recommendations in February 2012. The uploaded edition is the 2003 text incorporating amendments to October 2004. Recommendation numbering differs in the 2012 text. Record which edition you cited.

Sheet Factors and weights
A1: Inherent risk factors and weights
A2: Blue cells are inputs. Weights must total 100.
A4: ID | B4: Factor | C4: Weight | D4: FFIEC category | E4: Why this weight
A5: F1 | B5: Jurisdiction and geographic footprint | C5: 20 | D5: Geographic locations | E5: One of the four FFIEC categories. Weighted high because jurisdiction drives both sanctions exposure and the reliability of every other answer on the questionnaire.
A6: F2 | B6: Quality of supervision and regulatory standing | C6: 15 | D6: Customers and entities | E6: FATF Rec 7(a) makes this an explicit requirement for correspondent relationships. Weighted below jurisdiction because a well-supervised bank in a weak jurisdiction is still exposed to that jurisdiction.
A7: F3 | B7: Ownership and control transparency | C7: 20 | D7: Customers and entities | E7: FATF Rec 5(b) and Rec 33. Weighted equal to jurisdiction because an unresolvable ownership chain defeats every downstream control.
A8: F4 | B8: Physical presence and shell bank proximity | C8: 10 | D8: Customers and entities | E8: Weighted low because the extreme case is handled as a hard exclusion under Rec 18, not by the weighted model. This factor captures proximity, not the prohibition itself.
A9: F5 | B9: Products, services and delivery channels | C9: 25 | D9: Products and services | E9: Highest weight. FFIEC lists products and services first among the risk categories, and the CBDDQ devotes an entire section to it. Payable-through accounts and downstream correspondent relationships are the two specific exposures FATF Rec 7(e) singles out.
A10: F6 | B10: Customer base and PEP exposure | C10: 10 | D10: Customers and entities | E10: FATF Rec 6. Weighted low because PEP exposure is largely addressed by control C3 rather than by avoiding the relationship.
B11: Total | C11: =SUM(C5:C10) -> 100 | D11: =IF(C11=100,"OK","ERROR - weights must total 100") -> OK
A13: Inherent score anchors
A14: 0 | B14: Absent. The questionnaire states the condition does not apply, and the answer is internally consistent with the rest of the submission.
A15: 3 | B15: Present but contained. Low materiality, or fully offset by a structural feature such as an ultimate parent listed on a regulated exchange.
A16: 6 | B16: Present and material. The condition applies at a level that would draw an examiner question.
A17: 10 | B17: Present and severe, or undeterminable because the respondent did not answer.
A19: An unanswered question scores 10, not 0. Silence is not evidence of absence, and scoring it as low would reward non-disclosure.
A20: Inherent risk = sum over factors of (score / 10) x weight. Range 0 to 100.

Sheet Scoring criteria
A1: Written criteria for each anchor — the criteria decide, not the analyst
A3: ID | B3: Factor | C3: Score 0 | D3: Score 3 | E3: Score 6 | F3: Score 10
A4: F1 | B4: Jurisdiction and geographic footprint | C4: HQ and all branches in FATF member jurisdictions. No presence in any comprehensively sanctioned jurisdiction (Q108 No). | D4: HQ in a FATF member jurisdiction; one or more branches in an offshore financial centre that is itself supervised. | E4: HQ or a material branch in a jurisdiction outside the FATF membership with no equivalent regional assessment, or non-resident customers concentrated in such jurisdictions. | F4: Any presence in a jurisdiction subject to comprehensive sanctions, or in a jurisdiction FATF has identified as having strategic deficiencies, or Q2 and Q108 unanswered.
A5: F2 | B5: Quality of supervision and regulatory standing | C5: Named prudential regulator in a FATF member jurisdiction, LEI supplied, ultimate parent licensed or a listed holding company. | D5: Named regulator in a FATF member jurisdiction but LEI absent, or the ultimate parent is an unlicensed holding company with no separate disclosure. | E5: Regulator named but jurisdiction outside FATF membership, or the respondent discloses a past regulatory action without resolution detail. | F5: No regulator identified, or an unresolved money laundering or terrorist financing investigation or regulatory action as contemplated by FATF Rec 7(a), or Q10 unanswered.
A6: F3 | B6: Ownership and control transparency | C6: Ownership resolves to a company listed on a regulated exchange and subject to disclosure requirements. No bearer shares. FATF Interpretative Note to Rec 5 paragraph 10 supports reduced measures here. | D6: Privately held but every beneficial owner at 10 per cent or more is named, with no more than two intermediate layers, all in jurisdictions that maintain a beneficial ownership register. No bearer shares. | E6: Three or more intermediate layers, or one or more layers in a jurisdiction that does not publish beneficial ownership, or a beneficial owner named without a verifiable identifier. | F6: Any bearer shares in issue (FATF Rec 33), or no beneficial owner identifiable at the 10 per cent threshold, or Q6d1 unanswered.
A7: F4 | B7: Physical presence and shell bank proximity | C7: Registered and primary business addresses both stated and consistent. No offshore banking licence. No virtual bank licence. | D7: Single stated address, operations confirmed at that address, part of a regulated financial group. | E7: Operates under an offshore banking licence for one or more branches (Q8), or holds a virtual bank licence or serves solely through online channels (Q9). | F7: No verifiable physical presence in the licensing jurisdiction and not affiliated with a regulated financial group. Note: this meets the FATF Glossary definition of a shell bank and triggers the hard exclusion — see Hard exclusions sheet.
A8: F5 | B8: Products, services and delivery channels | C8: Retail or commercial banking only. No correspondent banking offered, no payable-through accounts, no cash-intensive or anonymity-favouring products. | D8: Private banking or wealth management offered, but no correspondent banking to third-party institutions and no payable-through accounts. | E8: Correspondent banking offered to foreign banks but downstream relationships not permitted, or two or more of: hold mail, virtual assets, cross-border bulk cash, low price securities, remote deposit capture. | F8: Payable-through accounts offered (FATF Rec 7(e)), or downstream correspondent relationships permitted without stated identification procedures, or correspondent services to MSBs or MVTS without downstream controls.
A9: F6 | B9: Customer base and PEP exposure | C9: No material non-resident customer base (Q15 No). PEPs screened at onboarding, renewal and on trigger events, with EDD applied. | D9: Non-resident customers above 10 per cent but concentrated in FATF member jurisdictions, with full PEP screening. | E9: Non-resident customers above 10 per cent with concentration outside FATF membership, or PEP screening at onboarding only with no trigger-event screening. | F9: No PEP screening programme, or restricted and prohibited customer categories not defined, or Q15 and Q71 unanswered.

Sheet Control multipliers
A1: Control effectiveness — four domains, multiplied together
A2: Blue cells are inputs. Multipliers are applied as a product, then floored.
A4: Evidence tier | B4: Multiplier | C4: What qualifies
A5: Independently evidenced | B5: 0.65 | C5: An external audit report, regulatory examination summary, or independent assurance opinion covering this domain has been supplied and is current. FATF Rec 15(c) contemplates an audit function to test the system; this tier requires the output of that function, not the assertion that it exists.
A6: Partially evidenced | B6: 0.82 | C6: The CBDDQ answer is supported by at least one document supplied by the respondent — a policy extract, a screening list inventory, a testing summary — but not by independent assurance.
A7: Self-asserted only | B7: 0.94 | C7: The respondent answered Yes on the CBDDQ and supplied nothing further. The questionnaire is a senior-level attestation and carries some weight, but it is the respondent describing itself.
A8: Absent or unanswered | B8: 1 | C8: The respondent answered No, answered Not Applicable where the domain plainly applies, or left the question blank. No reduction.
A11: Control domains
A12: ID | B12: Control domain | C12: FATF basis | D12: CBDDQ source
A13: C1 | B13: AML, CTF and sanctions programme with independent testing | C13: Rec 15 | D13: Q22a to Q22l, in particular Q22g independent testing
A14: C2 | B14: Customer due diligence and beneficial ownership | C14: Rec 5, Rec 10 | D14: Q22c, Q22e, Q22f, Q74 periodic review frequency
A15: C3 | B15: Sanctions and PEP screening | C15: Rec 6, Rec 13 | D15: Q70, Q72, Q106 sanctions lists, Q107 update timeliness
A16: C4 | B16: Correspondent and downstream relationship controls | C16: Rec 7, Rec 18 | D16: Q19a1c, Q19a1f, Q19h, Q76t, Q78
A19: Floor | B19: 0.2 | C19: Residual risk can never fall below this fraction of inherent risk, whatever the controls.
A20: Why the floor binds | C20: All four domains independently evidenced gives 0.65 to the fourth power = 0.1785, which is below the floor. So a respondent with a perfect control submission is still assessed at 20 per cent of its inherent risk. This is the arithmetic that implements the principle that controls never eliminate risk — it is not decorative.
A22: Residual bands
A23: Lower bound | B23: Band | C23: Consequence
A24: 0 | B24: Low | C24: Approved at Gate 2 by the analyst. No committee.
A25: 20 | B25: Moderate | C25: Approved at Gate 2 with conditions recorded. No committee.
A26: 40 | B26: High | C26: Escalates to Gate 3 committee. Senior management approval required, consistent with FATF Rec 7(c).
A27: 65 | B27: Prohibited pending exception | C27: Refused unless an executive exception is recorded with a written rationale and a review date.

Sheet Hard exclusions
A1: Binary stops applied before scoring
A2: These are prohibitions, not risk weights. They sit outside the model deliberately.
A4: Test | B4: Basis | C4: Determination logic | D4: Outcome
A5: Shell bank | B5: FATF Rec 18 and Glossary definition | C5: Respondent has no physical presence in the jurisdiction of incorporation AND is not affiliated with a regulated financial group. Derived from Q3, Q4, Q8, Q10 and Q12. | D5: Refuse. Not scored.
A6: Downstream shell bank exposure | B6: FATF Rec 18 | C6: Respondent permits downstream correspondent relationships AND has no stated procedure to identify them (Q19a1c or Q19a1f not Yes). | D6: Refuse pending remediation.
A7: Comprehensively sanctioned presence | B7: FATF Rec 21; sanctions regimes | C7: Q108 answered Yes — physical presence in a jurisdiction subject to comprehensive UN, OFAC, OFSI, EU or G7 sanctions. | D7: Refuse. Not scored.
A8: Respondent bank category prohibited | B8: Respondent own FCC programme, CBDDQ Q76 | C8: Respondent itself lists Respondent Banks or Shell banks as Prohibited under its own programme while seeking a correspondent relationship — an internal inconsistency requiring resolution before assessment. | D8: Return to Gate 1.
A11: Why these are outside the weighted model
A12: The FFIEC manual warns that no single indicator should be taken as determinative of a higher or lower risk profile, which is why nothing in the weighted model can push a case to prohibited on its own. But FATF Rec 18 is not phrased as a risk factor — it directs that financial institutions should refuse to enter into or continue a correspondent relationship with a shell bank. A prohibition cannot be expressed as a weight, because any weight implies it could be outscored by good answers elsewhere. Separating the two is the cleanest way to honour both documents, and it is the design decision most worth being able to explain.

Sheet Worked cases
A1: Three hand-calculated cases
A2: Case A is modelled on the profile in the uploaded CBDDQ V1.4 so extraction can be validated against a real document. Cases B and C are synthetic.
A4: ID | B4: Factor | C4: Weight | D4: A score | E4: A weighted | F4: B score | G4: B weighted | H4: C score | I4: C weighted | J4: Note on case A
A5: F1 | B5: ='Factors and weights'!B5 -> Jurisdiction and geographic footprint | C5: ='Factors and weights'!C5 -> 20 | D5: 3 | E5: =D5/10*$C5 -> 6 | F5: 10 | G5: =F5/10*$C5 -> 20 | H5: 10 | I5: =H5/10*$C5 -> 20 | J5: Swiss HQ, branches in Guernsey, Hong Kong SAR and Singapore. Guernsey is an offshore centre but supervised; Q108 answered No.
A6: F2 | B6: ='Factors and weights'!B6 -> Quality of supervision and regulatory standing | C6: ='Factors and weights'!C6 -> 15 | D6: 0 | E6: =D6/10*$C6 -> 0 | F6: 3 | G6: =F6/10*$C6 -> 4.5 | H6: 10 | I6: =H6/10*$C6 -> 15 | J6: FINMA named at Q10, LEI supplied at Q11. Ultimate parent is a holding company without its own licence (Q13), which is disclosed rather than concealed.
A7: F3 | B7: ='Factors and weights'!B7 -> Ownership and control transparency | C7: ='Factors and weights'!C7 -> 20 | D7: 0 | E7: =D7/10*$C7 -> 0 | F7: 10 | G7: =F7/10*$C7 -> 20 | H7: 10 | I7: =H7/10*$C7 -> 20 | J7: Q6d1: wholly owned by a group holding company listed on SIX with 100 per cent free float. Q7: no bearer shares. Interpretative Note to FATF Rec 5 paragraph 10 supports reduced measures for public companies subject to disclosure requirements.
A8: F4 | B8: ='Factors and weights'!B8 -> Physical presence and shell bank proximity | C8: ='Factors and weights'!C8 -> 10 | D8: 0 | E8: =D8/10*$C8 -> 0 | F8: 6 | G8: =F8/10*$C8 -> 6 | H8: 10 | I8: =H8/10*$C8 -> 10 | J8: Registered address stated at Q3. Q8 offshore banking licence No. Q9 virtual bank licence No.
A9: F5 | B9: ='Factors and weights'!B9 -> Products, services and delivery channels | C9: ='Factors and weights'!C9 -> 25 | D9: 6 | E9: =D9/10*$C9 -> 15 | F9: 6 | G9: =F9/10*$C9 -> 15 | H9: 10 | I9: =H9/10*$C9 -> 25 | J9: Q19a correspondent banking No and Q19h payable-through accounts No, which keeps this off 10. But hold mail, virtual assets, cross-border remittances, remote deposit capture and low price securities are all Yes.
A10: F6 | B10: ='Factors and weights'!B10 -> Customer base and PEP exposure | C10: ='Factors and weights'!C10 -> 10 | D10: 6 | E10: =D10/10*$C10 -> 6 | F10: 6 | G10: =F10/10*$C10 -> 6 | H10: 10 | I10: =H10/10*$C10 -> 10 | J10: Q15 Yes — material non-resident base. Q15a lists Hong Kong, Singapore, United Kingdom, Germany, Italy. Q71 to Q73 show PEP screening at onboarding, renewal and trigger event.
B11: Inherent risk | E11: =SUM(E5:E10) -> 27 | G11: =SUM(G5:G10) -> 71.5 | I11: =SUM(I5:I10) -> 100
B13: Control evidence tier
A14: C1 | B14: ='Control multipliers'!B13 -> AML, CTF and sanctions programme with independent testing | D14: Partially evidenced | E14: =INDEX('Control multipliers'!$B$5:$B$8,MATCH(D14,'Control multipliers'!$A$5:$A$8,0)) -> 0.82 | F14: Self-asserted only | G14: =INDEX('Control multipliers'!$B$5:$B$8,MATCH(F14,'Control multipliers'!$A$5:$A$8,0)) -> 0.94 | H14: Absent or unanswered | I14: =INDEX('Control multipliers'!$B$5:$B$8,MATCH(H14,'Control multipliers'!$A$5:$A$8,0)) -> 1 | J14: Q22g independent testing Yes, plus a testing summary supplied. No external audit report, so not the top tier.
A15: C2 | B15: ='Control multipliers'!B14 -> Customer due diligence and beneficial ownership | D15: Self-asserted only | E15: =INDEX('Control multipliers'!$B$5:$B$8,MATCH(D15,'Control multipliers'!$A$5:$A$8,0)) -> 0.94 | F15: Self-asserted only | G15: =INDEX('Control multipliers'!$B$5:$B$8,MATCH(F15,'Control multipliers'!$A$5:$A$8,0)) -> 0.94 | H15: Absent or unanswered | I15: =INDEX('Control multipliers'!$B$5:$B$8,MATCH(H15,'Control multipliers'!$A$5:$A$8,0)) -> 1 | J15: Q22c and Q22e Yes, nothing supplied beyond the questionnaire.
A16: C3 | B16: ='Control multipliers'!B15 -> Sanctions and PEP screening | D16: Partially evidenced | E16: =INDEX('Control multipliers'!$B$5:$B$8,MATCH(D16,'Control multipliers'!$A$5:$A$8,0)) -> 0.82 | F16: Self-asserted only | G16: =INDEX('Control multipliers'!$B$5:$B$8,MATCH(F16,'Control multipliers'!$A$5:$A$8,0)) -> 0.94 | H16: Absent or unanswered | I16: =INDEX('Control multipliers'!$B$5:$B$8,MATCH(H16,'Control multipliers'!$A$5:$A$8,0)) -> 1 | J16: Q106 lists UN, OFAC, OFSI, EU, G7 plus SECO and OSFI; Q107 states same day to two business days. The list inventory is a supplied document.
A17: C4 | B17: ='Control multipliers'!B16 -> Correspondent and downstream relationship controls | D17: Self-asserted only | E17: =INDEX('Control multipliers'!$B$5:$B$8,MATCH(D17,'Control multipliers'!$A$5:$A$8,0)) -> 0.94 | F17: Absent or unanswered | G17: =INDEX('Control multipliers'!$B$5:$B$8,MATCH(F17,'Control multipliers'!$A$5:$A$8,0)) -> 1 | H17: Absent or unanswered | I17: =INDEX('Control multipliers'!$B$5:$B$8,MATCH(H17,'Control multipliers'!$A$5:$A$8,0)) -> 1 | J17: Q19a correspondent banking is No, so the downstream questions are Please select throughout. Treated as self-asserted, not absent, because the service is not offered.
B18: Combined multiplier | E18: =E14*E15*E16*E17 -> 0.59413264 | G18: =G14*G15*G16*G17 -> 0.830584 | I18: =I14*I15*I16*I17 -> 1 | J18: Product of the four domain multipliers.
B19: Unfloored residual | E19: =E11*E18 -> 16.041581 | G19: =G11*G18 -> 59.386756 | I19: =I11*I18 -> 100
B20: Floor value | E20: =E11*'Control multipliers'!$B$19 -> 5.4 | G20: =G11*'Control multipliers'!$B$19 -> 14.3 | I20: =I11*'Control multipliers'!$B$19 -> 20
B21: Residual risk | E21: =MAX(E19,E20) -> 16.041581 | G21: =MAX(G19,G20) -> 59.386756 | I21: =MAX(I19,I20) -> 100
B22: Band | E22: =INDEX('Control multipliers'!$B$24:$B$27,MATCH(E21,'Control multipliers'!$A$24:$A$27,1)) -> Low | G22: =INDEX('Control multipliers'!$B$24:$B$27,MATCH(G21,'Control multipliers'!$A$24:$A$27,1)) -> High | I22: =INDEX('Control multipliers'!$B$24:$B$27,MATCH(I21,'Control multipliers'!$A$24:$A$27,1)) -> Prohibited pending exception
A24: Case identities
A25: A | B25: Alpine Trust Bank AG — Switzerland. Profile taken from the uploaded Wolfsberg CBDDQ V1.4. Expected outcome: Low. Use this as the extraction validation case, because the source document is real and every field can be checked against a numbered question.
A26: B | B26: Meridian Commercial Bank Ltd — synthetic. Jurisdiction with FATF-identified strategic deficiencies, three layers of holding companies through a jurisdiction with no beneficial ownership register, 15 per cent bearer shares, offshore banking licence on one branch, correspondent services to foreign banks. Expected outcome: High. Lands mid-band deliberately, not on a boundary.
A27: C | B27: Coastal Offshore Bank — synthetic. No verifiable physical presence, no regulator identified, bearer shares, payable-through accounts offered, no control evidence at all. Expected outcome: Prohibited by score AND refused by hard exclusion. Both routes should fire, which is what makes it a useful test of the two paths.
A29: Floor demonstration: if case C supplied independently evidenced controls in all four domains, the multiplier would be 0.65^4 = 0.179, giving an unfloored residual of 17.9 on an inherent of 100. The floor lifts it to 20.0 — still Moderate, never Low and never zero. Show this to the panel.

Sheet Calculator
A1: Score a new case
A2: Fill the blue cells only. Everything else calculates.
A4: Respondent name | C4: [enter name]
A5: Weights version used | C5: ='Change log'!A5 -> v0.1 | D5: Recorded on every assessment so a case re-renders with the weights that were live at the time.
A7: ID | B7: Factor | C7: Weight | D7: Score 0/3/6/10 | E7: Weighted | F7: Evidence — cite the CBDDQ question number
A8: ='Factors and weights'!A5 -> F1 | B8: ='Factors and weights'!B5 -> Jurisdiction and geographic footprint | C8: ='Factors and weights'!C5 -> 20 | D8: 0 | E8: =D8/10*C8 -> 0
A9: ='Factors and weights'!A6 -> F2 | B9: ='Factors and weights'!B6 -> Quality of supervision and regulatory standing | C9: ='Factors and weights'!C6 -> 15 | D9: 0 | E9: =D9/10*C9 -> 0
A10: ='Factors and weights'!A7 -> F3 | B10: ='Factors and weights'!B7 -> Ownership and control transparency | C10: ='Factors and weights'!C7 -> 20 | D10: 0 | E10: =D10/10*C10 -> 0
A11: ='Factors and weights'!A8 -> F4 | B11: ='Factors and weights'!B8 -> Physical presence and shell bank proximity | C11: ='Factors and weights'!C8 -> 10 | D11: 0 | E11: =D11/10*C11 -> 0
A12: ='Factors and weights'!A9 -> F5 | B12: ='Factors and weights'!B9 -> Products, services and delivery channels | C12: ='Factors and weights'!C9 -> 25 | D12: 0 | E12: =D12/10*C12 -> 0
A13: ='Factors and weights'!A10 -> F6 | B13: ='Factors and weights'!B10 -> Customer base and PEP exposure | C13: ='Factors and weights'!C10 -> 10 | D13: 0 | E13: =D13/10*C13 -> 0
B14: Inherent risk | E14: =SUM(E8:E13) -> 0
A16: ID | B16: Control domain | D16: Evidence tier | E16: Multiplier | F16: Evidence — what was supplied
A17: ='Control multipliers'!A13 -> C1 | B17: ='Control multipliers'!B13 -> AML, CTF and sanctions programme with independent testing | D17: Absent or unanswered | E17: =INDEX('Control multipliers'!$B$5:$B$8,MATCH(D17,'Control multipliers'!$A$5:$A$8,0)) -> 1
A18: ='Control multipliers'!A14 -> C2 | B18: ='Control multipliers'!B14 -> Customer due diligence and beneficial ownership | D18: Absent or unanswered | E18: =INDEX('Control multipliers'!$B$5:$B$8,MATCH(D18,'Control multipliers'!$A$5:$A$8,0)) -> 1
A19: ='Control multipliers'!A15 -> C3 | B19: ='Control multipliers'!B15 -> Sanctions and PEP screening | D19: Absent or unanswered | E19: =INDEX('Control multipliers'!$B$5:$B$8,MATCH(D19,'Control multipliers'!$A$5:$A$8,0)) -> 1
A20: ='Control multipliers'!A16 -> C4 | B20: ='Control multipliers'!B16 -> Correspondent and downstream relationship controls | D20: Absent or unanswered | E20: =INDEX('Control multipliers'!$B$5:$B$8,MATCH(D20,'Control multipliers'!$A$5:$A$8,0)) -> 1
B21: Combined multiplier | E21: =E17*E18*E19*E20 -> 1
B23: Unfloored residual | E23: =E14*E21 -> 0
B24: Floor value | E24: =E14*'Control multipliers'!$B$19 -> 0
B25: Residual risk | E25: =MAX(E23,E24) -> 0
B26: Band | E26: =INDEX('Control multipliers'!$B$24:$B$27,MATCH(E25,'Control multipliers'!$A$24:$A$27,1)) -> Low
A28: Hard exclusion check — run before relying on the band above
B29: Shell bank test — no physical presence and not affiliated with a regulated group | D29: No
B30: Downstream relationships permitted without identification procedures | D30: No
B31: Physical presence in a comprehensively sanctioned jurisdiction (Q108) | D31: No
B32: Outcome | D32: =IF(COUNTIF(D29:D31,"Yes")>0,"REFUSE - hard exclusion","Proceed on band") -> Proceed on band
A34: Enter Yes or No in the three cells above. Any Yes refuses the relationship regardless of the calculated band, because FATF Rec 18 is a prohibition rather than a weighted factor.

Sheet Change log
A1: Weights configuration version history
A2: Only the Risk Owner role may change a weight. Every change creates a new row. Assessments record the version that scored them.
A4: Version | B4: Date | C4: Changed by | D4: Field | E4: Old value | F4: New value | G4: Justification
A5: v0.1 | B5: 2026-09-16 | C5: [name] — draft | D5: Initial model | E5: n/a | F5: n/a | G5: First draft. Six factors derived from the four FFIEC risk categories, weighted per the Factors and weights sheet. Four control domains mapped to FATF Rec 5, 6, 7, 15 and 18. Not yet reviewed by the team.
G6: [next change goes here]
A8: This sheet is the paper version. In the application these rows live in a versioned configuration table, and the scoring engine records config_version_id against every assessment so a case from last month re-renders with the weights that were live when it was scored.
